app_creator/__init__.py
app_creator/cli.py
app_creator/urls.py
app_creator/views.py
app_creator_location-0.1.1.dist-info/METADATA
app_creator_location-0.1.1.dist-info/WHEEL
app_creator_location-0.1.1.dist-info/entry_points.txt
app_creator_location-0.1.1.dist-info/top_level.txt
app_creator_location-0.1.1.dist-info/RECORD
